xmljson/__init__.py
xmljson/__main__.py
xmljson-0.2.0.dist-info/DESCRIPTION.rst
xmljson-0.2.0.dist-info/LICENSE.txt
xmljson-0.2.0.dist-info/METADATA
xmljson-0.2.0.dist-info/RECORD
xmljson-0.2.0.dist-info/WHEEL
xmljson-0.2.0.dist-info/entry_points.txt
xmljson-0.2.0.dist-info/metadata.json
xmljson-0.2.0.dist-info/top_level.txt
