Metadata-Version: 1.1
Name: xmljson
Version: 0.2.0
Summary: Converts XML into JSON/Python dicts/arrays and vice-versa.
Home-page: https://github.com/sanand0/xmljson
Author: S Anand
Author-email: root.node@gmail.com
License: MIT
Keywords: xmljson
Platform: UNKNOWN
Classifier: Development Status :: 4 - Beta
Classifier: Intended Audience :: Developers
Classifier: License :: OSI Approved :: MIT License
Classifier: Operating System :: OS Independent
Classifier: Programming Language :: Python :: 2
Classifier: Programming Language :: Python :: 2.7
Classifier: Programming Language :: Python :: 3
Classifier: Programming Language :: Python :: 3.6
Classifier: Topic :: Software Development
Classifier: Topic :: Software Development :: Libraries :: Python Modules
